Transformer/BaseAttention.py
Transformer/CausalSelfAttention.py
Transformer/CrossAttention.py
Transformer/FeedForward.py
Transformer/GlobalAttention.py
Transformer/PositionalEmbedding.py
Transformer/Transformer.py
Transformer/__init__.py
Transformer/aux_functions.py
Transformer/decoder.py
Transformer/decoderLayer.py
Transformer/encoder.py
Transformer/encoderLayer.py
Transformer_lafae-0.0.6.dist-info/METADATA
Transformer_lafae-0.0.6.dist-info/WHEEL
Transformer_lafae-0.0.6.dist-info/top_level.txt
Transformer_lafae-0.0.6.dist-info/RECORD
