Metadata-Version: 2.1
Name: Transformer-lafae
Version: 0.0.6
Summary: Vanilla Regression Transformer
Home-page: UNKNOWN
Author: Luan Lopes
Author-email: luansantos@poli.ufrj.br
License: UNKNOWN
Keywords: python,transformer,Machine Learning
Platform: UNKNOWN
Classifier: Development Status :: 3 - Alpha
Classifier: Intended Audience :: Education
Classifier: Programming Language :: Python :: 3
Classifier: Operating System :: Microsoft :: Windows
